gym_killerviruses/__init__.py
gym_killerviruses/envs/__init__.py
gym_killerviruses/envs/actors.py
gym_killerviruses/envs/gameUtils.py
gym_killerviruses/envs/killerviruses_env.py
gym_killerviruses/envs/pandemic.py
gym_killerviruses-0.0.2.dist-info/LICENSE
gym_killerviruses-0.0.2.dist-info/METADATA
gym_killerviruses-0.0.2.dist-info/WHEEL
gym_killerviruses-0.0.2.dist-info/top_level.txt
gym_killerviruses-0.0.2.dist-info/RECORD
